{
    "RStudioAddIns::InsertComma": ",",
    "RStudioAddIns::InsertAssign": "Alt+/",
    "RStudioAddIns::InsertUpAssign": "Shift+Alt+/",
    "RStudioAddIns::InsertRustAssign": "Alt+'",
    "RStudioAddIns::InsertAssignRight": "Shift+Alt+'",
    "RStudioAddIns::InsertGoAssign": "Alt+;",
    "RStudioAddIns::InsertTilde": "Shift+Alt+;",
    "RStudioAddIns::InsertEqualEqual": "Alt+=",
    "RStudioAddIns::InsertPlus": "Shift+Alt+=",
    "RStudioAddIns::InsertEqual": "Alt+-",
    "RStudioAddIns::InsertMinus": "Shift+Alt+-",
    "RStudioAddIns::InsertTimes": "Alt+8",
    "RStudioAddIns::InsertDivide": "Shift+Alt+8",
    "RStudioAddIns::InsertLessThan": "Alt+,",
    "RStudioAddIns::InsertMoreThan": "Alt+.",
    "RStudioAddIns::InsertLessEqual": "Shift+Alt+,",
    "RStudioAddIns::InsertMoreEqual": "Shift+Alt+.",
    "RStudioAddIns::InsertInclude": "Shift+Alt+5",
    "RStudioAddIns::InsertPipeDplyr": "Alt+0",
    "RStudioAddIns::InsertPipeDplyrAssign": "Shift+Alt+0",
    "RStudioAddIns::InsertPipeDplyrVar": "Alt+9",
    "RStudioAddIns::InsertPipeDplyrTee": "Shift+Alt+9"
}
